eudata_server/__init__.py
eudata_server/__main__.py
eudata_server/api.py
eudata_server/assets/css/arno-web-styles.css
eudata_server/assets/css/dropdown.css
eudata_server/assets/css/error-styles.css
eudata_server/assets/css/grid-display.css
eudata_server/assets/css/grid-theme.css
eudata_server/assets/css/grid-theme.css.map
eudata_server/assets/css/map-styles.css
eudata_server/assets/css/tippy/light-border.css
eudata_server/assets/css/tippy/light.css
eudata_server/assets/css/tippy/material.css
eudata_server/assets/css/tippy/translucent-lgt-purple.css
eudata_server/assets/css/tippy/translucent-purple.css
eudata_server/assets/css/tippy/translucent.css
eudata_server/assets/js/ag-grid/ag-grid-community.amd.js
eudata_server/assets/js/ag-grid/ag-grid-community.amd.min.js
eudata_server/assets/js/ag-grid/ag-grid-community.amd.min.noStyle.js
eudata_server/assets/js/ag-grid/ag-grid-community.amd.noStyle.js
eudata_server/assets/js/ag-grid/ag-grid-community.auto.complete.esm.js
eudata_server/assets/js/ag-grid/ag-grid-community.auto.complete.esm.min.js
eudata_server/assets/js/ag-grid/ag-grid-community.auto.esm.js
eudata_server/assets/js/ag-grid/ag-grid-community.auto.esm.min.js
eudata_server/assets/js/ag-grid/ag-grid-community.cjs.js
eudata_server/assets/js/ag-grid/ag-grid-community.cjs.min.js
eudata_server/assets/js/ag-grid/ag-grid-community.esm.js
eudata_server/assets/js/ag-grid/ag-grid-community.esm.min.js
eudata_server/assets/js/ag-grid/ag-grid-community.js
eudata_server/assets/js/ag-grid/ag-grid-community.min.js
eudata_server/assets/js/ag-grid/ag-grid-community.min.noStyle.js
eudata_server/assets/js/ag-grid/ag-grid-community.noStyle.js
eudata_server/assets/js/three.r134.min.js
eudata_server/assets/js/vanta.globe.min.js
eudata_server/assets/js/vanta.net.min.js
eudata_server/assets/js/vanta.rings.min.js
eudata_server/assets/js/vanta.trunk.min.js
eudata_server/assets/political-compass/json/dozenvalues-ideologies.json
eudata_server-0.1.26.dist-info/entry_points.txt
eudata_server-0.1.26.dist-info/METADATA
eudata_server-0.1.26.dist-info/WHEEL
eudata_server-0.1.26.dist-info/RECORD
