Metadata-Version: 2.1
Name: eudata-server
Version: 0.1.26
Summary: 
Author: arnos-stuff
Author-email: bcda0276@gmail.com
Requires-Python: >=3.8,<4.0
Classifier: Programming Language :: Python :: 3
Classifier: Programming Language :: Python :: 3.8
Classifier: Programming Language :: Python :: 3.9
Classifier: Programming Language :: Python :: 3.10
Classifier: Programming Language :: Python :: 3.11
Requires-Dist: fastapi[all] (>=0.88.0,<0.89.0)
Requires-Dist: pandas (>=1.5.2,<2.0.0)
Requires-Dist: requests (>=2.28.1,<3.0.0)
Requires-Dist: rich (>=12.6.0,<13.0.0)
Requires-Dist: typer[all] (>=0.7.0,<0.8.0)
